graph_of_thoughts/__init__.py
graph_of_thoughts/controller/README.md
graph_of_thoughts/controller/__init__.py
graph_of_thoughts/controller/abstract_language_model.py
graph_of_thoughts/controller/chatgpt.py
graph_of_thoughts/controller/config_template.json
graph_of_thoughts/controller/controller.py
graph_of_thoughts/controller/llamachat_hf.py
graph_of_thoughts/operations/README.md
graph_of_thoughts/operations/__init__.py
graph_of_thoughts/operations/graph_of_operations.py
graph_of_thoughts/operations/operations.py
graph_of_thoughts/operations/thought.py
graph_of_thoughts/parser/__init__.py
graph_of_thoughts/parser/parser.py
graph_of_thoughts/prompter/__init__.py
graph_of_thoughts/prompter/prompter.py
graph_of_thoughts-0.0.2.dist-info/METADATA
graph_of_thoughts-0.0.2.dist-info/WHEEL
graph_of_thoughts-0.0.2.dist-info/licenses/LICENSE
graph_of_thoughts-0.0.2.dist-info/RECORD
