Metadata-Version: 2.1
Name: graph_of_thoughts
Version: 0.0.2
Summary: Python package for Graph of Thoughts that enables solving elaborate problems with Large Language Models
Project-URL: Homepage, https://github.com/spcl/graph-of-thoughts
Author-email: Maciej Besta <maciej.besta@inf.ethz.ch>, Nils Blach <nils.blach@inf.ethz.ch>, Ales Kubicek <akubicek@student.ethz.ch>, Robert Gerstenberger <gerstenberger.robert@gmail.com>
License: Copyright (c) 2023 ETH Zurich.
License-File: LICENSE
Classifier: Operating System :: OS Independent
Classifier: Programming Language :: Python :: 3
Requires-Python: >=3.8
Requires-Dist: accelerate>=0.21.0
Requires-Dist: backoff>=2.2.1
Requires-Dist: bitsandbytes>=0.41.0
Requires-Dist: matplotlib>=3.7.1
Requires-Dist: numpy>=1.24.3
Requires-Dist: openai>=0.27.7
Requires-Dist: pandas>=2.0.3
Requires-Dist: scipy>=1.10.1
Requires-Dist: sympy>=1.12
Requires-Dist: torch>=2.0.1
Requires-Dist: transformers>=4.31.0
